diagnostics/__init__.py
diagnostics/__version__.py
diagnostics/classes.py
diagnostics/errors.py
diagnostics/functions.py
diagnostics/log.py
pydiagnostics-0.6.0.dist-info/LICENSE
pydiagnostics-0.6.0.dist-info/METADATA
pydiagnostics-0.6.0.dist-info/WHEEL
pydiagnostics-0.6.0.dist-info/top_level.txt
pydiagnostics-0.6.0.dist-info/RECORD
