Metadata-Version: 2.1
Name: pydiagnostics
Version: 0.6.0
Summary: A toolbox to analyse diagnostic data!
Home-page: https://github.com/tim00w/diagnostics/
Author: Timo Lesterhuis
Author-email: timolesterhuis@gmail.com
License: MIT License
Project-URL: Documentation, https://diagnostics.readthedocs.io/en/latest/
Project-URL: Source, https://github.com/tim00w/diagnostics
Platform: UNKNOWN
Classifier: Programming Language :: Python :: 3 :: Only
Classifier: Programming Language :: Python :: 3.5
Classifier: Programming Language :: Python :: 3.6
Classifier: Programming Language :: Python :: 3.7
Classifier: License :: OSI Approved :: MIT License
Classifier: Operating System :: OS Independent
Requires-Dist: pytz (>=2018)
Requires-Dist: numpy (>=1.16.0)
Requires-Dist: matplotlib (>=3.0.0)
